production_request/__init__.py
production_request/api.py
production_request/base.py
production_request/celery_handlers.py
production_request/enums.py
production_request/kibana.py
production_request/loggers.py
production_request/middleware.py
production_request/processes.py
production_request/urls.py
production_request/utils.py
production_request/views.py
production_request/kibana_templates/00e3358b-2ad5-4105-a8f8-f78876c18b1b.json
production_request/kibana_templates/042005bc-1ab4-4139-9582-6ca1e08fb67d.json
production_request/kibana_templates/0ac8157f-70c5-404f-a219-5d7047a41aa6.json
production_request/kibana_templates/14bb8fb2-849a-4d88-81fc-9b1e221d374c.json
production_request/kibana_templates/339465aa-d599-47c9-a012-0a54f7371592.json
production_request/kibana_templates/3a512643-ea85-463d-b408-e2a527030178.json
production_request/kibana_templates/4dc730e6-5b8a-4946-b71d-b813b9db66df.json
production_request/kibana_templates/51e1b7b6-54d0-40b1-a3af-d3a453978643.json
production_request/kibana_templates/584cdda6-291b-4402-b7f1-2de3ba15f896.json
production_request/kibana_templates/64be2e2b-7009-4e79-b1bc-de7eda3bb7e7.json
production_request/kibana_templates/6b79ba24-7a52-4db1-93c1-3317d45b397f.json
production_request/kibana_templates/6f09dbaf-1fb8-457e-94ff-75e0efa71e6f.json
production_request/kibana_templates/77d1d261-5025-4f00-822e-ecce3a61886b.json
production_request/kibana_templates/841f8f54-2011-42d0-ae6b-c7cfd2586135.json
production_request/kibana_templates/84eb1ad1-72ce-481d-844f-94bf2f6029d3.json
production_request/kibana_templates/8c2d2451-7732-4bde-9fab-b45772311c02.json
production_request/kibana_templates/929f45e1-f584-40c5-9150-7ec864105243.json
production_request/kibana_templates/934140d7-538d-4cd3-9ca6-900eb3b3b459.json
production_request/kibana_templates/96d1a6b7-d47d-4002-9956-dc8a599d99c4.json
production_request/kibana_templates/a143eecb-30cf-4469-9510-c9842d0d15cd.json
production_request/kibana_templates/a7901d1d-8478-41ec-83ae-fdadb35095b5.json
production_request-0.7.0.dist-info/licenses/LICENSE.md
production_request-0.7.0.dist-info/METADATA
production_request-0.7.0.dist-info/WHEEL
production_request-0.7.0.dist-info/top_level.txt
production_request-0.7.0.dist-info/RECORD
