Metadata-Version: 2.4
Name: production-request
Version: 0.7.0
Summary: Metric collector for production
Author: Dmitriy Chernyshov
Author-email: dechernyshov@bars.group
License: BSD
Classifier: Development Status :: 5 - Production/Stable
Classifier: Intended Audience :: Developers
Classifier: Programming Language :: Python :: 3
License-File: LICENSE.md
Requires-Dist: django
Requires-Dist: psutil
Requires-Dist: celery
Requires-Dist: Jinja2
Requires-Dist: click
Dynamic: author
Dynamic: author-email
Dynamic: classifier
Dynamic: description
Dynamic: description-content-type
Dynamic: keywords
Dynamic: license
Dynamic: license-file
Dynamic: requires-dist
Dynamic: summary
